infi.recipe.console_scripts-0.5.5-py2.7-nspkg.pth
infi/recipe/console_scripts/Microsoft.VC90.CRT.manifest-x64
infi/recipe/console_scripts/Microsoft.VC90.CRT.manifest-x86
infi/recipe/console_scripts/__init__.py
infi/recipe/console_scripts/__version__.py
infi/recipe/console_scripts/egg.py
infi/recipe/console_scripts/embed-gui-x64.exe
infi/recipe/console_scripts/embed-gui-x86.exe
infi/recipe/console_scripts/embed-x64.exe
infi/recipe/console_scripts/embed-x86.exe
infi/recipe/console_scripts/embed3-gui-x64.exe
infi/recipe/console_scripts/embed3-gui-x86.exe
infi/recipe/console_scripts/embed3-x64.exe
infi/recipe/console_scripts/embed3-x86.exe
infi/recipe/console_scripts/minimal_packages.py
infi/recipe/console_scripts/msvcm90.dll-x64
infi/recipe/console_scripts/msvcm90.dll-x86
infi/recipe/console_scripts/msvcp90.dll-x64
infi/recipe/console_scripts/msvcp90.dll-x86
infi/recipe/console_scripts/msvcr90.dll-x64
infi/recipe/console_scripts/msvcr90.dll-x86
infi/recipe/console_scripts/virtualenv.py
infi/recipe/console_scripts/windows.py
infi.recipe.console_scripts-0.5.5.dist-info/LICENSE
infi.recipe.console_scripts-0.5.5.dist-info/METADATA
infi.recipe.console_scripts-0.5.5.dist-info/WHEEL
infi.recipe.console_scripts-0.5.5.dist-info/entry_points.txt
infi.recipe.console_scripts-0.5.5.dist-info/namespace_packages.txt
infi.recipe.console_scripts-0.5.5.dist-info/top_level.txt
infi.recipe.console_scripts-0.5.5.dist-info/RECORD
