Metadata-Version: 2.1
Name: infi.recipe.console-scripts
Version: 0.5.5
Summary: buildout recipe for generating better console and gui script for entry points
Home-page: https://github.com/Infinidat/infi.recipe.console_scripts
Author: Arnon Yaari
Author-email: arnony@infinidat.com
License: BSD
Platform: UNKNOWN
Classifier: Intended Audience :: Developers
Classifier: Intended Audience :: System Administrators
Classifier: License :: OSI Approved :: BSD License
Classifier: Operating System :: OS Independent
Classifier: Programming Language :: Python
Classifier: Programming Language :: Python :: 2
Classifier: Programming Language :: Python :: 3
Classifier: Topic :: Software Development :: Libraries :: Python Modules
Requires-Dist: setuptools (>=32.0)
Requires-Dist: zc.buildout
